setup.py
mygene/__init__.py
mygene/api.py
mygene/gene.py
mygene/metadata.py
mygene_api.egg-info/PKG-INFO
mygene_api.egg-info/SOURCES.txt
mygene_api.egg-info/dependency_links.txt
mygene_api.egg-info/requires.txt
mygene_api.egg-info/top_level.txt
tests/gene_test.py
tests/metadata_test.py