Metadata-Version: 1.0
Name: mygene-api
Version: 1.0
Summary: A simple API wrapper for the MyGene.info API.
Home-page: UNKNOWN
Author: Brian Schrader
Author-email: brian@biteofanapple.com
License: LICENSE.txt
Keywords: gene,genomics
Platform: UNKNOWN
